opengewe/__init__.py
opengewe/__main__.py
opengewe/client.py
opengewe/callback/__init__.py
opengewe/callback/factory.py
opengewe/callback/types.py
opengewe/callback/handlers/__init__.py
opengewe/callback/handlers/base.py
opengewe/callback/handlers/contact.py
opengewe/callback/handlers/file.py
opengewe/callback/handlers/group.py
opengewe/callback/handlers/link.py
opengewe/callback/handlers/location.py
opengewe/callback/handlers/media.py
opengewe/callback/handlers/payment.py
opengewe/callback/handlers/system.py
opengewe/callback/handlers/text.py
opengewe/callback/models/__init__.py
opengewe/callback/models/base.py
opengewe/callback/models/contact.py
opengewe/callback/models/file.py
opengewe/callback/models/group.py
opengewe/callback/models/link.py
opengewe/callback/models/location.py
opengewe/callback/models/media.py
opengewe/callback/models/payment.py
opengewe/callback/models/system.py
opengewe/callback/models/text.py
opengewe/logger/__init__.py
opengewe/logger/config.py
opengewe/logger/formatters.py
opengewe/logger/utils.py
opengewe/mixin/__init__.py
opengewe/mixin/message_mixin.py
opengewe/modules/__init__.py
opengewe/modules/account.py
opengewe/modules/contact.py
opengewe/modules/favorite.py
opengewe/modules/finder.py
opengewe/modules/group.py
opengewe/modules/login.py
opengewe/modules/message.py
opengewe/modules/personal.py
opengewe/modules/sns.py
opengewe/modules/tag.py
opengewe/queue/__init__.py
opengewe/queue/advanced.py
opengewe/queue/app.py
opengewe/queue/base.py
opengewe/queue/celery_worker.py
opengewe/queue/simple.py
opengewe/queue/tasks.py
opengewe/utils/decorators.py
opengewe/utils/event_manager.py
opengewe/utils/plugin_base.py
opengewe/utils/plugin_manager.py
opengewe/utils/singleton.py
opengewe-0.2.1.dist-info/licenses/LICENSE
opengewe-0.2.1.dist-info/METADATA
opengewe-0.2.1.dist-info/WHEEL
opengewe-0.2.1.dist-info/entry_points.txt
opengewe-0.2.1.dist-info/top_level.txt
opengewe-0.2.1.dist-info/RECORD
