Metadata-Version: 2.4
Name: opengewe
Version: 0.2.1
Summary: 基于Gewe和Gewechat的开源微信机器人异步框架，提供高性能的微信自动化解决方案
Author: Wangnov
License: MIT
Project-URL: Homepage, https://github.com/Wangnov/opengewe
Project-URL: Documentation, https://github.com/Wangnov/opengewe
Project-URL: Bug Tracker, https://github.com/Wangnov/opengewe/issues
Project-URL: Source Code, https://github.com/Wangnov/opengewe
Keywords: wechat,bot,automation,geweapi,weixin,async
Classifier: Development Status :: 4 - Beta
Classifier: Intended Audience :: Developers
Classifier: License :: OSI Approved :: MIT License
Classifier: Programming Language :: Python :: 3
Classifier: Programming Language :: Python :: 3.9
Classifier: Programming Language :: Python :: 3.10
Classifier: Programming Language :: Python :: 3.11
Classifier: Programming Language :: Python :: 3.12
Classifier: Programming Language :: Python :: 3.13
Classifier: Topic :: Communications :: Chat
Classifier: Topic :: Software Development :: Libraries :: Python Modules
Classifier: Operating System :: OS Independent
Requires-Python: >=3.9
License-File: LICENSE
Requires-Dist: qrcode>=8.1.0
Requires-Dist: aiohttp>=3.9.2
Requires-Dist: pytz>=2024.1
Requires-Dist: apscheduler>=3.10.0
Requires-Dist: loguru>=0.6.0
Requires-Dist: tomli>=2.0.0; python_version < "3.11"
Provides-Extra: advanced
Requires-Dist: celery>=5.3.0; extra == "advanced"
Requires-Dist: redis>=6.1.0; extra == "advanced"
Requires-Dist: amqp>=5.3.1; extra == "advanced"
Provides-Extra: full
Requires-Dist: celery>=5.3.0; extra == "full"
Requires-Dist: redis>=6.1.0; extra == "full"
Requires-Dist: amqp>=5.3.1; extra == "full"
Dynamic: license-file
